fileunity_workbooks/__init__.py
fileunity_workbooks-0.1.1.dist-info/LICENSE.txt
fileunity_workbooks-0.1.1.dist-info/METADATA
fileunity_workbooks-0.1.1.dist-info/WHEEL
fileunity_workbooks-0.1.1.dist-info/top_level.txt
fileunity_workbooks-0.1.1.dist-info/RECORD
