Metadata-Version: 2.1
Name: fileunity-workbooks
Version: 0.1.1
Summary: fileunity for openpyxl workbooks
Author-email: Johannes <johannes-programming@posteo.org>
License: The MIT License (MIT)
Project-URL: Download, https://pypi.org/project/fileunity-workbooks/#files
Project-URL: Source, https://github.com/johannes-programming/fileunity_workbooks
Classifier: License :: OSI Approved :: MIT License
Classifier: Programming Language :: Python
Classifier: Programming Language :: Python :: 3
Requires-Python: >=3.11
License-File: LICENSE.txt
Requires-Dist: fileunity >=1.3
Requires-Dist: openpyxl >=3.0.10
